LICENSE
MANIFEST.in
README.md
requirements-test.txt
requirements.txt
setup.py
padl_ext/__init__.py
padl_ext/version.py
padl_ext/pytorch_lightning/__init__.py
padl_ext/pytorch_lightning/prepare.py
padl_ext/torchserve/__init__.py
padl_ext/torchserve/handler.py
padl_ext/torchserve/prepare.py
padl_ext/trainer/__init__.py
padl_ext/trainer/trainer.py
padl_extensions.egg-info/PKG-INFO
padl_extensions.egg-info/SOURCES.txt
padl_extensions.egg-info/dependency_links.txt
padl_extensions.egg-info/requires.txt
padl_extensions.egg-info/top_level.txt
tests/__init__.py
tests/unittests/__init__.py
tests/unittests/torchserve/__init__.py
tests/unittests/torchserve/test_torchserve.py