Metadata-Version: 2.1
Name: padl-extensions
Version: 0.1.5
Summary: Extensions for pytorch abstractions for deep learning
Home-page: https://github.com/lf1-io/padl-extensions
Author: LF1
Author-email: contact@lf1.io
License: Apache 2.0
Platform: UNKNOWN
Classifier: Programming Language :: Python :: 3.8
Classifier: Programming Language :: Python :: 3.9
Classifier: Topic :: Scientific/Engineering
Classifier: Topic :: Scientific/Engineering :: Artificial Intelligence
Requires-Python: >=3.8
Provides-Extra: all
Provides-Extra: pytorch_lightning
Provides-Extra: torchserve
Provides-Extra: trainer
License-File: LICENSE
